venv/bin/activate_this.py
venv/bin/jp.py
venv/bin/rst2html.py
venv/bin/rst2html4.py
venv/bin/rst2html5.py
venv/bin/rst2latex.py
venv/bin/rst2man.py
venv/bin/rst2odt.py
venv/bin/rst2odt_prepstyles.py
venv/bin/rst2pseudoxml.py
venv/bin/rst2s5.py
venv/bin/rst2xetex.py
venv/bin/rst2xml.py
venv/bin/rstpep2html.py
webflow_aws/__init__.py
webflow_aws/app.py
webflow_aws/global_variables.py
webflow_aws/webflow_aws_tool.py
webflow_aws/backend/__init__.py
webflow_aws/backend/component.py
webflow_aws/backend/compute/__init__.py
webflow_aws/backend/compute/infrastructure.py
webflow_aws/backend/compute/functions/index.checkLanguage.js
webflow_aws/backend/compute/functions/index.s3TriggerArtifactsUpload.js
webflow_aws/backend/compute/functions/package.json
webflow_aws/backend/compute/functions/yarn.lock
webflow_aws/backend/networking/__init__.py
webflow_aws/backend/networking/infrastructure.py
webflow_aws/backend/networking/functions/editPathForOrigin.js
webflow_aws/backend/storage/__init__.py
webflow_aws/backend/storage/infrastructure.py
webflow_aws/utils/__init__.py
webflow_aws/utils/base_utils.py
webflow_aws/utils/config_maker.py
webflow_aws-2.0.1.dist-info/LICENSE
webflow_aws-2.0.1.dist-info/METADATA
webflow_aws-2.0.1.dist-info/WHEEL
webflow_aws-2.0.1.dist-info/entry_points.txt
webflow_aws-2.0.1.dist-info/top_level.txt
webflow_aws-2.0.1.dist-info/RECORD
