Metadata-Version: 2.1
Name: webflow-aws
Version: 2.0.1
Summary: Deploy your Webflow static website on AWS
Home-page: https://github.com/odfdata/webflow-aws
Author: odfdata
Author-email: fc@oracleofde.fi
License: Apache License 2.0
Classifier: Development Status :: 5 - Production/Stable
Classifier: Natural Language :: English
Classifier: License :: OSI Approved :: Apache Software License
Classifier: Programming Language :: Python :: 3.6
Classifier: Operating System :: OS Independent
Requires-Python: >=3.6
License-File: LICENSE
Requires-Dist: boto3 (~=1.26.29)
Requires-Dist: pyyaml (~=6.0)
Requires-Dist: aws-cdk-lib (~=2.54.0)
Requires-Dist: Click (~=8.1.3)
Requires-Dist: tqdm (~=4.64.1)
Requires-Dist: emoji (~=2.2.0)
